{"name": "../imedd-political-speech-data-test/speeches1/Androulakis/Androulakis,Sparti,2023-03-26", "value": 250, "children": [{"name": "location", "value": 44, "children": [{"name": "greek society", "value": 1}, {"name": "sparta", "value": 1}, {"name": "peloponnese", "value": 2}, {"name": "maximos building", "value": 1}, {"name": "greece", "value": 7}, {"name": "europe", "value": 8}, {"name": "parliament", "value": 1}, {"name": "village", "value": 1}, {"name": "city", "value": 1}, {"name": "european countries", "value": 2}, {"name": "crete", "value": 1}, {"name": "laconia", "value": 3}, {"name": "central europe", "value": 1}, {"name": "africa", "value": 1}, {"name": "southern greece", "value": 1}, {"name": "constitution", "value": 1}, {"name": "agios nikolaos", "value": 1}, {"name": "rhodes", "value": 1}, {"name": "country", "value": 4}, {"name": "2. country", "value": 1}, {"name": "tempe", "value": 1}, {"name": "athens", "value": 2}, {"name": "thessaloniki", "value": 1}]}, {"name": "group of people", "value": 32, "children": [{"name": "social justice", "value": 2}, {"name": "national dignity", "value": 1}, {"name": "greek people", "value": 5}, {"name": "oligarchy", "value": 3}, {"name": "democratic party", "value": 1}, {"name": "human lives", "value": 1}, {"name": "railway network", "value": 1}, {"name": "2. mps", "value": 1}, {"name": "european peoples", "value": 1}, {"name": "europeans", "value": 1}, {"name": "greeks", "value": 1}, {"name": "athenians", "value": 1}, {"name": "thessalonians", "value": 1}, {"name": "portuguese", "value": 1}, {"name": "friends", "value": 1}, {"name": "academic staff", "value": 1}, {"name": "children of the greek people", "value": 1}, {"name": "100 students", "value": 1}, {"name": "greek children", "value": 2}, {"name": "workers", "value": 1}, {"name": "small and medium-sized enterprises", "value": 1}, {"name": "68 powerful people", "value": 1}, {"name": "cost of living", "value": 1}, {"name": "progressive democrats", "value": 1}]}, {"name": "political party", "value": 21, "children": [{"name": "oligarchy", "value": 1}, {"name": "democratic party", "value": 2}, {"name": "syriza", "value": 5}, {"name": "syriza-independent greeks", "value": 1}, {"name": "pasok", "value": 1}, {"name": "prime minister", "value": 1}, {"name": "third party", "value": 1}, {"name": "far right", "value": 1}, {"name": "new democracy", "value": 3}, {"name": "european social democratic party", "value": 1}, {"name": "european socialist party", "value": 1}, {"name": "european state", "value": 1}, {"name": "social democracy of 2023", "value": 1}, {"name": "patriotic issue", "value": 1}]}, {"name": "person", "value": 32, "children": [{"name": "mitsotakis", "value": 3}, {"name": "mr mitsotakis", "value": 8}, {"name": "mr tsipras", "value": 3}, {"name": "andreas papandreou", "value": 2}, {"name": "mr. tsipras", "value": 1}, {"name": "mr. mitsotakis", "value": 1}, {"name": "mr. patsis", "value": 1}, {"name": "mr patsis", "value": 1}, {"name": "prime minister", "value": 2}, {"name": "1. mr karamanlis", "value": 1}, {"name": "politician", "value": 1}, {"name": "george gennimatas", "value": 1}, {"name": "paraskevas avgerinos", "value": 1}, {"name": "card", "value": 1}, {"name": "mrs kerameos", "value": 1}, {"name": "karamanlis", "value": 1}, {"name": "karatzaferis", "value": 1}, {"name": "kammenos", "value": 1}, {"name": "tsipras", "value": 1}]}, {"name": "date", "value": 18, "children": [{"name": "national elections", "value": 5}, {"name": "2019", "value": 1}, {"name": "2020", "value": 1}, {"name": "2022", "value": 1}, {"name": "04/10/21", "value": 1}, {"name": "month ago", "value": 1}, {"name": "2 months ago", "value": 1}, {"name": "2023", "value": 2}, {"name": "euros", "value": 1}, {"name": "400 million", "value": 1}, {"name": "pandemic", "value": 1}, {"name": "\u20ac1.2 billion", "value": 1}, {"name": "8 years", "value": 1}]}, {"name": "organization", "value": 68, "children": [{"name": "constitution", "value": 3}, {"name": "special court", "value": 1}, {"name": "pasok", "value": 2}, {"name": "railway of greece", "value": 1}, {"name": "european railway agency", "value": 1}, {"name": "transparency", "value": 1}, {"name": "ministry mr. karamanlis", "value": 1}, {"name": "corruption exists", "value": 1}, {"name": "european", "value": 2}, {"name": "41 million euros", "value": 1}, {"name": "54 million", "value": 1}, {"name": "3. ose", "value": 1}, {"name": "4. ministry of su", "value": 1}, {"name": "6. d.a.", "value": 1}, {"name": "european commission", "value": 1}, {"name": "european court of justice", "value": 1}, {"name": "political establishment", "value": 1}, {"name": "justice", "value": 1}, {"name": "nhs", "value": 2}, {"name": "lehman brothers", "value": 1}, {"name": "european economic fund of european economic sovereignty", "value": 1}, {"name": "europe", "value": 2}, {"name": "recovery and resilience fund", "value": 1}, {"name": "summit", "value": 1}, {"name": "trainose", "value": 1}, {"name": "government", "value": 1}, {"name": "oligarchy", "value": 1}, {"name": "establishment", "value": 1}, {"name": "bankruptcy", "value": 1}, {"name": "networks", "value": 1}, {"name": "20 billion recovery fund", "value": 1}, {"name": "welfare state", "value": 1}, {"name": "universities", "value": 2}, {"name": "university police", "value": 1}, {"name": "university", "value": 2}, {"name": "european programmes", "value": 1}, {"name": "security unit", "value": 1}, {"name": "police", "value": 1}, {"name": "greek university", "value": 1}, {"name": "private university", "value": 1}, {"name": "tourism industry", "value": 1}, {"name": "greek tourism", "value": 1}, {"name": "gavroglou", "value": 1}, {"name": "erasmus", "value": 1}, {"name": "master's degree", "value": 1}, {"name": "private ieks", "value": 1}, {"name": "public tourism schools", "value": 1}, {"name": "development", "value": 1}, {"name": "economic interests", "value": 1}, {"name": "daddy state", "value": 1}, {"name": "rulers of the day", "value": 1}, {"name": "labor rights", "value": 1}, {"name": "recovery fund", "value": 1}, {"name": "1. banks", "value": 1}, {"name": "greek state", "value": 1}, {"name": "greek budget", "value": 1}, {"name": "enfia", "value": 1}, {"name": "european programs", "value": 1}, {"name": "greece of the future", "value": 1}, {"name": "time", "value": 1}]}, {"name": "country", "value": 32, "children": [{"name": "greece", "value": 13}, {"name": "5. greek", "value": 1}, {"name": "china", "value": 1}, {"name": "portugal", "value": 2}, {"name": "spain", "value": 2}, {"name": "germany", "value": 4}, {"name": "italians", "value": 1}, {"name": "greek", "value": 3}, {"name": "austria", "value": 1}, {"name": "italy", "value": 1}, {"name": "belgium", "value": 1}, {"name": "holland", "value": 1}, {"name": "england", "value": 1}]}, {"name": "1% interest rate", "value": 1, "children": [{"name": "1", "value": 1}]}, {"name": "number", "value": 1, "children": [{"name": "4.8 million", "value": 1}]}, {"name": "000 \u20ac", "value": 1, "children": [{"name": "800", "value": 1}]}]}