{"name": "Mitsotakis,Chania,2023-04-22", "value": 255, "children": [{"name": "group of people", "value": 30, "children": [{"name": "chaniots", "value": 1}, {"name": "neo-democrats of crete", "value": 1}, {"name": "citizens", "value": 3}, {"name": "greek society", "value": 1}, {"name": "greeks", "value": 2}, {"name": "pensioners", "value": 1}, {"name": "businesses", "value": 1}, {"name": "households", "value": 1}, {"name": "livestock farmers", "value": 1}, {"name": "tourism", "value": 1}, {"name": "culture", "value": 1}, {"name": "greenery", "value": 1}, {"name": "minoan palaces", "value": 1}, {"name": "chanians", "value": 1}, {"name": "friends", "value": 2}, {"name": "immigrants", "value": 1}, {"name": "greek women", "value": 2}, {"name": "greek", "value": 1}, {"name": "civil servants", "value": 2}, {"name": "young people", "value": 1}, {"name": "young kids", "value": 1}, {"name": "5. young children", "value": 1}, {"name": "turkish", "value": 1}, {"name": "society", "value": 1}]}, {"name": "location", "value": 79, "children": [{"name": "crete", "value": 20}, {"name": "island", "value": 2}, {"name": "chania", "value": 12}, {"name": "evros", "value": 5}, {"name": "europe", "value": 2}, {"name": "heraklion", "value": 1}, {"name": "hersonissos", "value": 1}, {"name": "neapolis", "value": 1}, {"name": "kissamos", "value": 2}, {"name": "sitia", "value": 2}, {"name": "sfakia", "value": 1}, {"name": "paleochora", "value": 1}, {"name": "agios nikolaos", "value": 1}, {"name": "gavdos", "value": 1}, {"name": "kastelli", "value": 1}, {"name": "tavronitis", "value": 1}, {"name": "platanias", "value": 1}, {"name": "keriti", "value": 1}, {"name": "messara", "value": 1}, {"name": "white mountains", "value": 2}, {"name": "apatity mountains", "value": 1}, {"name": "municipal market", "value": 1}, {"name": "city's swimming pool", "value": 1}, {"name": "markopoulou camp", "value": 1}, {"name": "city", "value": 1}, {"name": "country", "value": 3}, {"name": "greece", "value": 3}, {"name": "souda", "value": 1}, {"name": "ionian sea", "value": 1}, {"name": "egypt", "value": 1}, {"name": "tempe", "value": 1}, {"name": "80 hospitals", "value": 1}, {"name": "156 health centres", "value": 1}, {"name": "3. brussels", "value": 1}, {"name": "7. public land", "value": 1}, {"name": "bulgaria", "value": 1}]}, {"name": "person", "value": 28, "children": [{"name": "president of the republic", "value": 1}, {"name": "konstantinos mitsotakis", "value": 1}, {"name": "marika mitsotaki", "value": 1}, {"name": "constantine", "value": 1}, {"name": "helen", "value": 1}, {"name": "citizens", "value": 1}, {"name": "katrougalos", "value": 1}, {"name": "farmers", "value": 1}, {"name": "nikos kazantzakis", "value": 1}, {"name": "prime minister", "value": 1}, {"name": "minister of culture", "value": 1}, {"name": "constantine mitsotakis", "value": 1}, {"name": "papadimoulis", "value": 1}, {"name": "eleftherios venizelos", "value": 1}, {"name": "greek woman", "value": 1}, {"name": "greek man", "value": 1}, {"name": "mr. tsipras", "value": 2}, {"name": "pappa", "value": 1}, {"name": "vincent cornaros", "value": 1}, {"name": "mr.", "value": 1}, {"name": "tsipras", "value": 2}, {"name": "prime minister mitsotakis", "value": 1}, {"name": "prime minister tsipras", "value": 1}, {"name": "i", "value": 1}, {"name": "varoufakis", "value": 1}, {"name": "god", "value": 1}]}, {"name": "organization", "value": 69, "children": [{"name": "parliament", "value": 3}, {"name": "presidential decree", "value": 1}, {"name": "government", "value": 3}, {"name": "envat", "value": 1}, {"name": "election commitment", "value": 1}, {"name": "parental benefit tax", "value": 1}, {"name": "businesses", "value": 1}, {"name": "eurostat", "value": 1}, {"name": "investment grade", "value": 1}, {"name": "lending", "value": 1}, {"name": "public debt", "value": 1}, {"name": "motorways of the sea", "value": 1}, {"name": "irrigation projects", "value": 1}, {"name": "souda naval station", "value": 1}, {"name": "government of the new democracy", "value": 1}, {"name": "unesco", "value": 1}, {"name": "library", "value": 1}, {"name": "europe", "value": 1}, {"name": "community", "value": 1}, {"name": "115 battle wing", "value": 1}, {"name": "rafale fighters", "value": 1}, {"name": "f-16 viper fighters", "value": 1}, {"name": "helicopters", "value": 1}, {"name": "armor", "value": 1}, {"name": "ammunition", "value": 1}, {"name": "greek defence industry", "value": 1}, {"name": "economic prosperity", "value": 1}, {"name": "national sovereignty", "value": 1}, {"name": "national rights", "value": 1}, {"name": "election programme", "value": 1}, {"name": "national health system", "value": 2}, {"name": "150 million euros", "value": 1}, {"name": "education system", "value": 1}, {"name": "model and experimental schools", "value": 1}, {"name": "recovery fund", "value": 2}, {"name": "universities", "value": 1}, {"name": "state", "value": 2}, {"name": "civil protection", "value": 1}, {"name": "112", "value": 1}, {"name": "gov.gr", "value": 2}, {"name": "emak", "value": 1}, {"name": "efka", "value": 1}, {"name": "new democracy", "value": 1}, {"name": "european", "value": 1}, {"name": "asep (agency for public administration)", "value": 1}, {"name": "unned", "value": 1}, {"name": "polytechnic", "value": 1}, {"name": "public sector", "value": 1}, {"name": "private sector", "value": 1}, {"name": "my house", "value": 1}, {"name": "2. us congress", "value": 1}, {"name": "4. european", "value": 1}, {"name": "6. modern apartments", "value": 1}, {"name": "8. private funds", "value": 1}, {"name": "9. real estate", "value": 1}, {"name": "10. 68 arms projects", "value": 1}, {"name": "11. migration", "value": 1}, {"name": "special court", "value": 1}, {"name": "golden dawn", "value": 1}, {"name": "syriza", "value": 1}, {"name": "democracy", "value": 1}]}, {"name": "political party", "value": 10, "children": [{"name": "new democracy", "value": 6}, {"name": "syriza", "value": 3}, {"name": "pasok", "value": 1}]}, {"name": "date", "value": 22, "children": [{"name": "may 21", "value": 3}, {"name": "n/a", "value": 1}, {"name": "50 billion", "value": 1}, {"name": "july 19", "value": 1}, {"name": "2015-2019", "value": 1}, {"name": "2023", "value": 2}, {"name": "2022", "value": 1}, {"name": "may 10", "value": 1}, {"name": "2027", "value": 1}, {"name": "no", "value": 1}, {"name": "2019", "value": 2}, {"name": "12 years", "value": 1}, {"name": "5th grade", "value": 1}, {"name": "today", "value": 1}, {"name": "wednesday", "value": 1}, {"name": "21 may", "value": 2}, {"name": "september", "value": 1}]}, {"name": "country", "value": 17, "children": [{"name": "greece", "value": 10}, {"name": "ukraine", "value": 1}, {"name": "greek", "value": 2}, {"name": "united states", "value": 1}, {"name": "turkey", "value": 1}, {"name": "1. greece", "value": 1}, {"name": "my country", "value": 1}]}]}