[{"topic": "privatization", "counts": 13, "freq": 0.3939393939393939}, {"topic": "other", "counts": 8, "freq": 0.24242424242424243}, {"topic": "political parties", "counts": 3, "freq": 0.09090909090909091}, {"topic": "elections", "counts": 2, "freq": 0.06060606060606061}, {"topic": "employment", "counts": 1, "freq": 0.030303030303030304}, {"topic": "debt", "counts": 1, "freq": 0.030303030303030304}, {"topic": "europe", "counts": 1, "freq": 0.030303030303030304}, {"topic": "infrastructure", "counts": 1, "freq": 0.030303030303030304}, {"topic": "democracy", "counts": 1, "freq": 0.030303030303030304}, {"topic": "health", "counts": 1, "freq": 0.030303030303030304}, {"topic": "corruption", "counts": 1, "freq": 0.030303030303030304}]