[{"topic": "privatization", "subtopic": "hospital privatization", "counts": 6, "freq": 0.18181818181818182}, {"topic": "privatization", "subtopic": "other", "counts": 4, "freq": 0.12121212121212122}, {"topic": "privatization", "subtopic": "privatization of public goods", "counts": 2, "freq": 0.06060606060606061}, {"topic": "privatization", "subtopic": "nationalization", "counts": 1, "freq": 0.030303030303030304}, {"topic": "other", "subtopic": "other", "counts": 4, "freq": 0.12121212121212122}, {"topic": "other", "subtopic": "troika", "counts": 1, "freq": 0.030303030303030304}, {"topic": "other", "subtopic": "railway", "counts": 1, "freq": 0.030303030303030304}, {"topic": "other", "subtopic": "youth", "counts": 1, "freq": 0.030303030303030304}, {"topic": "other", "subtopic": "election spending", "counts": 1, "freq": 0.030303030303030304}, {"topic": "political parties", "subtopic": "troika", "counts": 2, "freq": 0.06060606060606061}, {"topic": "political parties", "subtopic": "other", "counts": 1, "freq": 0.030303030303030304}, {"topic": "elections", "subtopic": "youth", "counts": 1, "freq": 0.030303030303030304}, {"topic": "elections", "subtopic": "election spending", "counts": 1, "freq": 0.030303030303030304}, {"topic": "employment", "subtopic": "railway", "counts": 1, "freq": 0.030303030303030304}, {"topic": "debt", "subtopic": "troika", "counts": 1, "freq": 0.030303030303030304}, {"topic": "europe", "subtopic": "railway", "counts": 1, "freq": 0.030303030303030304}, {"topic": "infrastructure", "subtopic": "railway", "counts": 1, "freq": 0.030303030303030304}, {"topic": "democracy", "subtopic": "police violence", "counts": 1, "freq": 0.030303030303030304}, {"topic": "health", "subtopic": "children", "counts": 1, "freq": 0.030303030303030304}, {"topic": "corruption", "subtopic": "corruption", "counts": 1, "freq": 0.030303030303030304}]